Metadata-Version: 2.1
Name: th2-grpc-act-ui-framework-win-demo
Version: 1.1.0.dev1048701896
Summary: th2_grpc_act_ui_framework_win_demo
Home-page: https://github.com/th2-net/th2-grpc-act-ui-framework-demo
Author: TH2-devs
Author-email: th2-devs@exactprosystems.com
License: Apache License 2.0
Platform: UNKNOWN
Requires-Python: >=3.7
